{
  "raye": "female",
  "death cab for cutie": "male",
  "the all-american rejects": "male",
  "hugel": "male",
  "daft punk": "male",
  "barry can't swim": "male",
  "noah kahan": "male",
  "burna boy": "male",
  "anderson .paak": "male",
  "myles frost": "male",
  "hozier": "male",
  "olive klug": "non-binary",
  "tyla": "female",
  "tyler childers": "male",
  "michael jackson": "male",
  "beyonc\u00e9": "female",
  "led zeppelin": "male",
  "jason isbell and the 400 unit": "male",
  "the beach boys": "male",
  "sturgill simpson": "male",
  "will smith": "male",
  "paul simon": "male",
  "khalid": "male",
  "big wild": "male",
  "tedeschi trucks band": "female",
  "my morning jacket": "male",
  "tems": "female",
  "jason isbell": "male",
  "ayra starr": "female",
  "polo & pan": "male",
  "omah lay": "male",
  "kaytranada": "male",
  "jamie xx": "male",
  "kyle watson": "male",
  "tekno": "male",
  "the chicks": "female",
  "brooks & dunn": "male",
  "rema": "male",
  "kehlani": "non-binary",
  "no doubt": "female",
  "juan luis guerra 4.40": "male",
  "bonnie raitt": "female",
  "little simz": "female",
  "rosal\u00eda": "female",
  "magoo": "male",
  "lily allen": "female",
  "khruangbin": "female",
  "billy strings": "male",
  "taylor swift": "female",
  "mariah carey": "female",
  "karol g": "female",
  "lindsey stirling": "female",
  "fetty wap": "male",
  "louis armstrong": "male",
  "keyshia cole": "female",
  "cynthia erivo": "female",
  "japanese breakfast": "female",
  "gorillaz": "male",
  "kanye west": "male",
  "girl talk": "male",
  "laufey": "female",
  "olivia dean": "female",
  "the cranberries": "female",
  "lucy dacus": "female",
  "boygenius": "female",
  "elderbrook": "male",
  "lana del rey": "female",
  "chappell roan": "female",
  "trent reznor and atticus ross": "male",
  "ariana grande": "female",
  "phoebe bridgers": "female",
  "sabrina carpenter": "female",
  "sofi tukker": "female",
  "dua lipa": "female",
  "troye sivan": "male",
  "sza": "female",
  "billie eilish": "non-binary",
  "annie dirusso": "female",
  "kendrick lamar": "male",
  "red hot chili peppers": "male",
  "frank ocean": "male",
  "kacey musgraves": "female",
  "sierra ferrell": "female",
  "andr\u00e9 de shields": "male",
  "radiohead": "male",
  "simon & garfunkel": "male",
  "fisher": "male",
  "reeve carney": "male",
  "fletcher": "female",
  "wizthemc": "male",
  "mark ronson": "male",
  "glen campbell": "male",
  "phish": "male",
  "regard": "male",
  "the meters": "male",
  "grateful dead": "male",
  "wyclef jean": "male",
  "hot since 82": "male",
  "hayley williams": "female",
  "o-town": "male",
  "lido pimienta": "female",
  "mel torm\u00e9": "male",
  "vintage culture": "male",
  "gwen stefani": "female",
  "florrie": "female",
  "daler mehndi": "male",
  "del amitri": "male",
  "lola young": "female",
  "tkay maidza": "female",
  "dom dolla": "male",
  "rvssian": "male",
  "zerb": "male",
  "mj lenderman": "male",
  "iyaz": "male",
  "abba": "female",
  "david guetta": "male",
  "major lazer": "male",
  "remi wolf": "female",
  "larry sparks": "male",
  "odesza": "male",
  "cass\u00f6": "male",
  "flawed mangoes": "male",
  "elio": "female",
  "sampha": "male",
  "marc benjamin": "male",
  "drama": "male",
  "ben platt": "male",
  "jay wheeler": "male",
  "emilia jones": "female",
  "babe rainbow": "male",
  "nicki minaj": "female",
  "elvin bishop": "male",
  "boney m.": "female",
  "twin shadow": "male",
  "james vincent mcmorrow": "male",
  "minnie riperton": "female",
  "bleachers": "male",
  "kamasi washington": "male",
  "cam clarke": "male",
  "goldlink": "male",
  "john prine": "male",
  "robert earl keen": "male",
  "john butler trio": "male",
  "jeff buckley": "male",
  "johnny cash": "male",
  "snatam kaur": "female",
  "rihanna": "female",
  "marshmello": "male",
  "post malone": "male",
  "armin van buuren": "male",
  "meshell ndegeocello": "female",
  "r. kelly": "male",
  "aaliyah": "female",
  "alec benjamin": "male",
  "chvrches": "female",
  "jamila woods": "female",
  "cautious clay": "male",
  "j balvin": "male",
  "sabrina claudio": "female",
  "drake": "male",
  "junglepussy": "female",
  "john adams": "male",
  "ryuichi sakamoto": "male",
  "loredana bert\u00e8": "female",
  "frank glazer": "male",
  "alessio bax": "male",
  "andr\u00e9 laplante": "male",
  "sufjan stevens": "male",
  "marco armani": "male",
  "franco battiato": "male",
  "the psychedelic furs": "male",
  "trixie mattel": "male",
  "thelonious monk": "male",
  "the japanese house": "female",
  "mary lou williams": "female",
  "ice spice": "female",
  "grouper": "female",
  "charly black": "male",
  "mochakk": "male",
  "mitski": "female",
  "julien baker": "female",
  "maggie rogers": "female",
  "biig piig": "female",
  "muna": "female",
  "catto": "non-binary",
  "pabllo vittar": "non-binary",
  "liniker": "female",
  "nickodemus": "male",
  "carson miller": "male",
  "paolo nutini": "male",
  "kesha": "female",
  "tom misch": "male",
  "daniel caesar": "male",
  "lizzo": "female",
  "cardi b": "female",
  "masego": "male",
  "daddy yankee": "male",
  "big freedia": "female",
  "destiny's child": "female",
  "monica martin": "female",
  "brockhampton": "male",
  "ozuna": "male",
  "shakira": "female",
  "amber mark": "female",
  "flight facilities": "male",
  "l\u00e9on": "female",
  "boyz ii men": "male",
  "sir": "male",
  "knox fortune": "male",
  "matoma": "male",
  "maluma": "male",
  "betty who": "non-binary",
  "sean paul": "male",
  "greta van fleet": "male",
  "lake street dive": "female",
  "arctic monkeys": "male",
  "the lumineers": "female",
  "jack johnson": "male",
  "tom petty": "male",
  "zedd": "male",
  "bad bunny": "male",
  "kc & the sunshine band": "male",
  "charli xcx": "female",
  "absolutely": "female",
  "daryl hall & john oates": "male",
  "kirby": "female",
  "paloma mami": "female",
  "tyler, the creator": "male",
  "grossomoddo": "male",
  "franc moody": "female",
  "disclosure": "male",
  "sir woman": "female",
  "rainbow kitten surprise": "female",
  "greensky bluegrass": "male",
  "terror/cactus": "male",
  "vandelux": "male",
  "young cardamom": "male",
  "the brook & the bluff": "male",
  "men i trust": "female",
  "tommy lefroy": "male",
  "afrospin": "male",
  "the the": "male",
  "clay street unit": "male",
  "telenova": "female",
  "watchhouse": "female",
  "tokyo tea room": "male",
  "the chemical brothers": "male",
  "raffa guido": "male",
  "jungle": "male",
  "lf system": "male",
  "soaked oats": "male",
  "tors": "male",
  "bear's den": "male",
  "firecityfunk": "male",
  "kukuni": "male",
  "original broadway cast of hamilton": "female",
  "sotomayor": "male",
  "the lil smokies": "male",
  "caamp": "male",
  "judah & the lion": "male",
  "phox": "female",
  "sister sparrow": "female",
  "sister sparow": "female",
  "the isley brothers": "male",
  "isley, jasper, isley": "male",
  "wacomo": "male",
  "outkast": "male",
  "lord huron": "male",
  "great lake swimmers": "male",
  "bandolero": "male",
  "giorgio moroder & joe esposito": "male",
  "f.r. david": "male",
  "valeria szerv\u00e1nszky": "female",
  "black country, new road": "female",
  "the trap remix guys": "male",
  "her's": "male",
  "madeline hawthorne": "female",
  "jakub zytecki": "male",
  "slow pulp": "female",
  "durand jones & the indications": "male",
  "better oblivion community center": "female",
  "peter cat recording co.": "male",
  "chartreuse": "male",
  "potyguara bardo": "male",
  "chon": "male",
  "glass animals": "male",
  "twiddle": "male",
  "big red machine": "male",
  "ty dolla $ign": "male",
  "bj the chicago kid": "male",
  "wet": "female",
  "cool company": "female",
  "brasstracks": "male",
  "bombay bicycle club": "male",
  "fleetwood mac": "female"
}